unexpected_isaves/__init__.py
unexpected_isaves/blocks.json
unexpected_isaves/save_image.py
unexpected_isaves/excel/__init__.py
unexpected_isaves/excel/excel.py
unexpected_isaves/rubiks/__init__.py
unexpected_isaves/rubiks/rubiks.py
unexpected_isaves-2.2.0.dist-info/LICENSE
unexpected_isaves-2.2.0.dist-info/METADATA
unexpected_isaves-2.2.0.dist-info/WHEEL
unexpected_isaves-2.2.0.dist-info/top_level.txt
unexpected_isaves-2.2.0.dist-info/RECORD
