Metadata-Version: 2.1
Name: unexpected_isaves
Version: 2.2.0
Summary: A Python library that paints an image on a spreadsheet, builds its pixel art in Minecraft, makes its ascii art, or makes a rubik's cube art out of it.
Author-email: Eric Mendes <ericvelasco.2000@gmail.com>, Henrique Souza <henriquesoliveira05@gmail.com>
Maintainer-email: Eric Mendes <ericvelasco.2000@gmail.com>
License: MIT License
Project-URL: Homepage, https://github.com/Eric-Mendes/unexpected-isaves
Project-URL: Bug Reports, https://github.com/Eric-Mendes/unexpected-isaves/issues
Project-URL: Source, https://github.com/Eric-Mendes/unexpected-isaves
Keywords: minecraft,pixel,art,excel,spreadsheet,ascii,rubiks
Classifier: Development Status :: 5 - Production/Stable
Classifier: Intended Audience :: Other Audience
Classifier: Topic :: Artistic Software
Classifier: License :: OSI Approved :: MIT License
Classifier: Programming Language :: Python :: 3
Classifier: Programming Language :: Python :: 3.8
Classifier: Programming Language :: Python :: 3.9
Classifier: Programming Language :: Python :: 3.10
Classifier: Programming Language :: Python :: 3.11
Classifier: Programming Language :: Python :: 3 :: Only
Requires-Python: >=3.8
License-File: LICENSE
Requires-Dist: pandas >=1.3.5
Requires-Dist: numpy >=1.21.5
Requires-Dist: Pillow >=8.4.0
Requires-Dist: openpyxl >=3.0.9
Requires-Dist: matplotlib >=3.5.1
Provides-Extra: dev
Requires-Dist: black ; extra == 'dev'
